Metadata-Version: 2.1
Name: physics-equations
Version: 0.0.4
Summary: physics-equations
Home-page: UNKNOWN
Author: FrenchFries8854
Author-email: frenchfries8854@gmail.com
License: MIT
Keywords: physics
Platform: UNKNOWN
Classifier: Development Status :: 5 - Production/Stable
Classifier: Intended Audience :: Education
Classifier: Operating System :: Microsoft :: Windows :: Windows 10
Classifier: License :: OSI Approved :: MIT License
Classifier: Programming Language :: Python :: 3
License-File: LICENSE.txt
